<?xml version="1.0" encoding="utf-8"?>
<Script xmlns:xsi="http://www.w3.org/2001/XMLSchema-instance" xmlns:xsd="http://www.w3.org/2001/XMLSchema">
  <Commands>
    <ScriptAction>
      <ScriptCommand xsi:type="CommentCommand" CommandID="108d369e-946a-4ff1-95d0-49cdef7a0588" CommandName="CommentCommand" IsCommented="false" SelectionName="Comment" DefaultPause="0" LineNumber="1" PauseBeforeExeucution="false" v_Comment="Create Formatted DateTime From Calculated Unix DateTime command sample" CommandEnabled="true" />
    </ScriptAction>
    <ScriptAction>
      <ScriptCommand xsi:type="CommentCommand" CommandID="fe6f9f72-cfb0-4889-87f0-f8c989d170e7" CommandName="CommentCommand" IsCommented="false" SelectionName="Comment" DefaultPause="0" LineNumber="2" PauseBeforeExeucution="false" v_Comment="Add 2 days on 2025/02/28" CommandEnabled="true" />
    </ScriptAction>
    <ScriptAction>
      <ScriptCommand xsi:type="GetFormattedDateTimeFromCalculatedUnixDateTimeCommand" CommandID="b9672868-fa68-4d54-9f03-9e5503b62aa3" CommandName="GetFormattedDateTimeFromCalculatedUnixDateTimeCommand" IsCommented="false" SelectionName="Get Formatted DateTime From Calculated Unix DateTime" DefaultPause="0" LineNumber="3" PauseBeforeExeucution="false" CommandEnabled="true" v_DateTime="1740700800" v_Result="vText" v_CalculationMethod="Add Days" v_Value="2" v_Format="MM/dd/yyyy" />
    </ScriptAction>
    <ScriptAction>
      <ScriptCommand xsi:type="ShowMessageCommand" CommandID="fcf7f7d8-16d3-4c05-80f8-7c8b3c051cdf" CommandName="ShowMessageCommand" IsCommented="false" SelectionName="Show Message" DefaultPause="0" LineNumber="4" PauseBeforeExeucution="false" CommandEnabled="true" v_Message="⦃vText⦄" v_AutoCloseAfter="0" v_FontName="" v_FontSize="" />
    </ScriptAction>
  </Commands>
  <Info>
    <TasktVersion>3.5.2.31</TasktVersion>
    <Author />
    <LastRunTime>2025-05-31T21:18:35.2325921+09:00</LastRunTime>
    <RunTimes>5</RunTimes>
    <Revision>8</Revision>
    <ScriptVersion>0.0.0</ScriptVersion>
    <Description />
  </Info>
  <Variables>
    <ScriptVariable>
      <VariableName>vText</VariableName>
      <VariableValue xsi:type="xsd:string"></VariableValue>
    </ScriptVariable>
  </Variables>
</Script>